build/lib/build/lib/build/lib/build/lib/build/lib/pypicor/__init__.py
build/lib/build/lib/build/lib/build/lib/build/lib/pypicor/baq.py
build/lib/build/lib/build/lib/build/lib/build/lib/pypicor/credentials.py
build/lib/build/lib/build/lib/build/lib/pypicor/__init__.py
build/lib/build/lib/build/lib/build/lib/pypicor/baq.py
build/lib/build/lib/build/lib/build/lib/pypicor/credentials.py
build/lib/build/lib/build/lib/pypicor/__init__.py
build/lib/build/lib/build/lib/pypicor/baq.py
build/lib/build/lib/build/lib/pypicor/credentials.py
build/lib/build/lib/pypicor/__init__.py
build/lib/build/lib/pypicor/baq.py
build/lib/build/lib/pypicor/credentials.py
build/lib/pypicor/__init__.py
build/lib/pypicor/baq.py
build/lib/pypicor/credentials.py
pypicor/__init__.py
pypicor/baq.py
pypicor/credentials.py
Pypicor-1.0.4.dist-info/METADATA
Pypicor-1.0.4.dist-info/WHEEL
Pypicor-1.0.4.dist-info/top_level.txt
Pypicor-1.0.4.dist-info/RECORD
